[
  {
    "Size": "SS01",
    "ID": "S0901",
    "Brand": "Samsung",
    "Model Name": "Galaxy S9",
    "Color": "Lilac Purple",
    "Color Code": "SC01",
    "Height": 147.7,
    "Width": 68.7,
    "Depth": 8.5,
    "image": "",
    "cal": "",
    "script": ""
  },
  {
    "Size": "SS01",
    "ID": "S0902",
    "Brand": "Samsung",
    "Model Name": "Galaxy S9",
    "Color": "Midnight Black",
    "Color Code": "SC02",
    "Height": 147.7,
    "Width": 68.7,
    "Depth": 8.5,
    "image": "",
    "cal": "",
    "script": ""
  },
  {
    "Size": "SS01",
    "ID": "S0903",
    "Brand": "Samsung",
    "Model Name": "Galaxy S9",
    "Color": "Titanium Gray",
    "Color Code": "SC03",
    "Height": 147.7,
    "Width": 68.7,
    "Depth": 8.5,
    "image": "",
    "cal": "",
    "script": ""
  },
  {
    "Size": "SS01",
    "ID": "S0904",
    "Brand": "Samsung",
    "Model Name": "Galaxy S9",
    "Color": "Coral Blue",
    "Color Code": "SC04",
    "Height": 147.7,
    "Width": 68.7,
    "Depth": 8.5,
    "image": "",
    "cal": "",
    "script": ""
  },
  {
    "Size": "SS01",
    "ID": "S0905",
    "Brand": "Samsung",
    "Model Name": "Galaxy S9",
    "Color": "Sunrise Gold",
    "Color Code": "SC05",
    "Height": 147.7,
    "Width": 68.7,
    "Depth": 8.5,
    "image": "",
    "cal": "",
    "script": ""
  },
  {
    "Size": "SS01",
    "ID": "S0906",
    "Brand": "Samsung",
    "Model Name": "Galaxy S9",
    "Color": "Burgundy Red",
    "Color Code": "SC06",
    "Height": 147.7,
    "Width": 68.7,
    "Depth": 8.5,
    "image": "",
    "cal": "",
    "script": ""
  },
  {
    "Size": "SS01",
    "ID": "S0907",
    "Brand": "Samsung",
    "Model Name": "Galaxy S9",
    "Color": "Polaris Blue",
    "Color Code": "SC07",
    "Height": 147.7,
    "Width": 68.7,
    "Depth": 8.5,
    "image": "",
    "cal": "",
    "script": ""
  },
  {
    "Size": "SS02",
    "ID": "S0911",
    "Brand": "Samsung",
    "Model Name": "Galaxy S9+",
    "Color": "Lilac Purple",
    "Color Code": "SC01",
    "Height": 158.1,
    "Width": 73.8,
    "Depth": 8.5,
    "image": "",
    "cal": "",
    "script": ""
  },
  {
    "Size": "SS02",
    "ID": "S0912",
    "Brand": "Samsung",
    "Model Name": "Galaxy S9+",
    "Color": "Midnight Black",
    "Color Code": "SC02",
    "Height": 158.1,
    "Width": 73.8,
    "Depth": 8.5,
    "image": "",
    "cal": "",
    "script": ""
  },
  {
    "Size": "SS02",
    "ID": "S0913",
    "Brand": "Samsung",
    "Model Name": "Galaxy S9+",
    "Color": "Titanium Gray",
    "Color Code": "SC03",
    "Height": 158.1,
    "Width": 73.8,
    "Depth": 8.5,
    "image": "",
    "cal": "",
    "script": ""
  },
  {
    "Size": "SS02",
    "ID": "S0914",
    "Brand": "Samsung",
    "Model Name": "Galaxy S9+",
    "Color": "Coral Blue",
    "Color Code": "SC04",
    "Height": 158.1,
    "Width": 73.8,
    "Depth": 8.5,
    "image": "",
    "cal": "",
    "script": ""
  },
  {
    "Size": "SS02",
    "ID": "S0915",
    "Brand": "Samsung",
    "Model Name": "Galaxy S9+",
    "Color": "Sunrise Gold",
    "Color Code": "SC05",
    "Height": 158.1,
    "Width": 73.8,
    "Depth": 8.5,
    "image": "",
    "cal": "",
    "script": ""
  },
  {
    "Size": "SS02",
    "ID": "S0916",
    "Brand": "Samsung",
    "Model Name": "Galaxy S9+",
    "Color": "Burgundy Red",
    "Color Code": "SC06",
    "Height": 158.1,
    "Width": 73.8,
    "Depth": 8.5,
    "image": "",
    "cal": "",
    "script": ""
  },
  {
    "Size": "SS02",
    "ID": "S0917",
    "Brand": "Samsung",
    "Model Name": "Galaxy S9+",
    "Color": "Polaris Blue",
    "Color Code": "SC07",
    "Height": 158.1,
    "Width": 73.8,
    "Depth": 8.5,
    "image": "",
    "cal": "",
    "script": ""
  },
  {
    "Size": "SS03",
    "ID": "S0921",
    "Brand": "Samsung",
    "Model Name": "Galaxy Note9",
    "Color": "Midnight Black",
    "Color Code": "SC02",
    "Height": 161.9,
    "Width": 76.4,
    "Depth": 8.8,
    "image": "",
    "cal": "",
    "script": ""
  },
  {
    "Size": "SS03",
    "ID": "S0922",
    "Brand": "Samsung",
    "Model Name": "Galaxy Note9",
    "Color": "Ocean Blue",
    "Color Code": "SC08",
    "Height": 161.9,
    "Width": 76.4,
    "Depth": 8.8,
    "image": "",
    "cal": "",
    "script": ""
  },
  {
    "Size": "SS03",
    "ID": "S0923",
    "Brand": "Samsung",
    "Model Name": "Galaxy Note9",
    "Color": "Lavender Purple",
    "Color Code": "SC09",
    "Height": 161.9,
    "Width": 76.4,
    "Depth": 8.8,
    "image": "",
    "cal": "",
    "script": ""
  },
  {
    "Size": "SS03",
    "ID": "S0924",
    "Brand": "Samsung",
    "Model Name": "Galaxy Note9",
    "Color": "Metallic Copper",
    "Color Code": "SC10",
    "Height": 161.9,
    "Width": 76.4,
    "Depth": 8.8,
    "image": "",
    "cal": "",
    "script": ""
  },
  {
    "Size": "SS03",
    "ID": "S0925",
    "Brand": "Samsung",
    "Model Name": "Galaxy Note9",
    "Color": "Cloud Silver",
    "Color Code": "SC11",
    "Height": 161.9,
    "Width": 76.4,
    "Depth": 8.8,
    "image": "",
    "cal": "",
    "script": ""
  },
  {
    "Size": "SS03",
    "ID": "S0926",
    "Brand": "Samsung",
    "Model Name": "Galaxy Note9",
    "Color": "Alpine White",
    "Color Code": "SC12",
    "Height": 161.9,
    "Width": 76.4,
    "Depth": 8.8,
    "image": "",
    "cal": "",
    "script": ""
  },
  {
    "Size": "SS04",
    "ID": "S1001",
    "Brand": "Samsung",
    "Model Name": "Galaxy S10",
    "Color": "Prism White",
    "Color Code": "SC13",
    "Height": 149.9,
    "Width": 70.4,
    "Depth": 7.8,
    "image": "",
    "cal": "",
    "script": ""
  },
  {
    "Size": "SS04",
    "ID": "S1002",
    "Brand": "Samsung",
    "Model Name": "Galaxy S10",
    "Color": "Prism Black",
    "Color Code": "SC14",
    "Height": 149.9,
    "Width": 70.4,
    "Depth": 7.8,
    "image": "",
    "cal": "",
    "script": ""
  },
  {
    "Size": "SS04",
    "ID": "S1003",
    "Brand": "Samsung",
    "Model Name": "Galaxy S10",
    "Color": "Prism Green",
    "Color Code": "SC15",
    "Height": 149.9,
    "Width": 70.4,
    "Depth": 7.8,
    "image": "",
    "cal": "",
    "script": ""
  },
  {
    "Size": "SS04",
    "ID": "S1004",
    "Brand": "Samsung",
    "Model Name": "Galaxy S10",
    "Color": "Prism Blue",
    "Color Code": "SC16",
    "Height": 149.9,
    "Width": 70.4,
    "Depth": 7.8,
    "image": "",
    "cal": "",
    "script": ""
  },
  {
    "Size": "SS05",
    "ID": "S1011",
    "Brand": "Samsung",
    "Model Name": "Galaxy S10+",
    "Color": "Prism White",
    "Color Code": "SC13",
    "Height": 157.6,
    "Width": 74.1,
    "Depth": 7.8,
    "image": "",
    "cal": "",
    "script": ""
  },
  {
    "Size": "SS05",
    "ID": "S1012",
    "Brand": "Samsung",
    "Model Name": "Galaxy S10+",
    "Color": "Prism Black",
    "Color Code": "SC14",
    "Height": 157.6,
    "Width": 74.1,
    "Depth": 7.8,
    "image": "",
    "cal": "",
    "script": ""
  },
  {
    "Size": "SS05",
    "ID": "S1013",
    "Brand": "Samsung",
    "Model Name": "Galaxy S10+",
    "Color": "Prism Green",
    "Color Code": "SC15",
    "Height": 157.6,
    "Width": 74.1,
    "Depth": 7.8,
    "image": "",
    "cal": "",
    "script": ""
  },
  {
    "Size": "SS05",
    "ID": "S1014",
    "Brand": "Samsung",
    "Model Name": "Galaxy S10+",
    "Color": "Prism Blue",
    "Color Code": "SC16",
    "Height": 157.6,
    "Width": 74.1,
    "Depth": 7.8,
    "image": "",
    "cal": "",
    "script": ""
  },
  {
    "Size": "SS05",
    "ID": "S1015",
    "Brand": "Samsung",
    "Model Name": "Galaxy S10+",
    "Color": "Ceramic White",
    "Color Code": "SC17",
    "Height": 157.6,
    "Width": 74.1,
    "Depth": 7.8,
    "image": "",
    "cal": "",
    "script": ""
  },
  {
    "Size": "SS05",
    "ID": "S1016",
    "Brand": "Samsung",
    "Model Name": "Galaxy S10+",
    "Color": "Ceramic Black",
    "Color Code": "SC18",
    "Height": 157.6,
    "Width": 74.1,
    "Depth": 7.8,
    "image": "",
    "cal": "",
    "script": ""
  },
  {
    "Size": "AS01",
    "ID": "A0501",
    "Brand": "Apple",
    "Model Name": "iPhone 5",
    "Color": "Black",
    "Color Code": "AC01",
    "Height": 123.8,
    "Width": 58.6,
    "Depth": 7.6,
    "image": "iphone5_Black.jpg",
    "cal": "",
    "script": ""
  },
  {
    "Size": "AS01",
    "ID": "A0502",
    "Brand": "Apple",
    "Model Name": "iPhone 5",
    "Color": "White",
    "Color Code": "AC02",
    "Height": 123.8,
    "Width": 58.6,
    "Depth": 7.6,
    "image": "iphone5_White.jpg",
    "cal": "",
    "script": ""
  },
  {
    "Size": "AS01",
    "ID": "A0511",
    "Brand": "Apple",
    "Model Name": "iPhone 5S",
    "Color": "Space Gray",
    "Color Code": "AC01",
    "Height": 123.8,
    "Width": 58.6,
    "Depth": 7.6,
    "image": "iPhone5S_gray.jpg",
    "cal": "",
    "script": ""
  },
  {
    "Size": "AS01",
    "ID": "A0512",
    "Brand": "Apple",
    "Model Name": "iPhone 5S",
    "Color": "White with silver trim",
    "Color Code": "AC02",
    "Height": 123.8,
    "Width": 58.6,
    "Depth": 7.6,
    "image": "iPhone5S_SilverTrim.jpg",
    "cal": "",
    "script": ""
  },
  {
    "Size": "AS01",
    "ID": "A0513",
    "Brand": "Apple",
    "Model Name": "iPhone 5S",
    "Color": "White with gold trim",
    "Color Code": "AC03",
    "Height": 123.8,
    "Width": 58.6,
    "Depth": 7.6,
    "image": "iPhone5S_GoldTrim.jpg",
    "cal": "",
    "script": ""
  },
  {
    "Size": "AS02",
    "ID": "A0601",
    "Brand": "Apple",
    "Model Name": "iPhone 6",
    "Color": "Gold",
    "Color Code": "AC04",
    "Height": 138.1,
    "Width": 67,
    "Depth": 6.9,
    "image": "iPhone6_Gold.jpg",
    "cal": "",
    "script": ""
  },
  {
    "Size": "AS02",
    "ID": "A0602",
    "Brand": "Apple",
    "Model Name": "iPhone 6",
    "Color": "Gray",
    "Color Code": "AC05",
    "Height": 138.1,
    "Width": 67,
    "Depth": 6.9,
    "image": "iPhone6_Gray.jpg",
    "cal": "",
    "script": ""
  },
  {
    "Size": "AS02",
    "ID": "A0603",
    "Brand": "Apple",
    "Model Name": "iPhone 6",
    "Color": "Silver",
    "Color Code": "AC06",
    "Height": 138.1,
    "Width": 67,
    "Depth": 6.9,
    "image": "iPhone6_Silver.jpg",
    "cal": "",
    "script": ""
  },
  {
    "Size": "AS03",
    "ID": "A0611",
    "Brand": "Apple",
    "Model Name": "iPhone 6 Plus",
    "Color": "Gold",
    "Color Code": "AC04",
    "Height": 158.1,
    "Width": 77.8,
    "Depth": 7.1,
    "image": "iPhone6Plus_Gold.jpg",
    "cal": "",
    "script": ""
  },
  {
    "Size": "AS03",
    "ID": "A0612",
    "Brand": "Apple",
    "Model Name": "iPhone 6 Plus",
    "Color": "Gray",
    "Color Code": "AC05",
    "Height": 158.1,
    "Width": 77.8,
    "Depth": 7.1,
    "image": "iPhone6Plus_Gray.jpg",
    "cal": "",
    "script": ""
  },
  {
    "Size": "AS03",
    "ID": "A0613",
    "Brand": "Apple",
    "Model Name": "iPhone 6 Plus",
    "Color": "Silver",
    "Color Code": "AC06",
    "Height": 158.1,
    "Width": 77.8,
    "Depth": 7.1,
    "image": "iPhone6Plus_Silver.jpg",
    "cal": "",
    "script": ""
  },
  {
    "Size": "AS02",
    "ID": "A0621",
    "Brand": "Apple",
    "Model Name": "iPhone 6S",
    "Color": "Gold",
    "Color Code": "AC04",
    "Height": 138.3,
    "Width": 67.1,
    "Depth": 7.1,
    "image": "iphone6s_gold.jpg",
    "cal": "",
    "script": ""
  },
  {
    "Size": "AS02",
    "ID": "A0622",
    "Brand": "Apple",
    "Model Name": "iPhone 6S",
    "Color": "Gray",
    "Color Code": "AC05",
    "Height": 138.3,
    "Width": 67.1,
    "Depth": 7.1,
    "image": "iphone6s_gray.jpg",
    "cal": "",
    "script": ""
  },
  {
    "Size": "AS02",
    "ID": "A0623",
    "Brand": "Apple",
    "Model Name": "iPhone 6S",
    "Color": "Rose Gold",
    "Color Code": "AC07",
    "Height": 138.3,
    "Width": 67.1,
    "Depth": 7.1,
    "image": "iPhone6S_RoseGold.jpg",
    "cal": "",
    "script": ""
  },
  {
    "Size": "AS02",
    "ID": "A0624",
    "Brand": "Apple",
    "Model Name": "iPhone 6S",
    "Color": "Silver",
    "Color Code": "AC06",
    "Height": 138.3,
    "Width": 67.1,
    "Depth": 7.1,
    "image": "iPhone6S_Silver.jpg",
    "cal": "",
    "script": ""
  },
  {
    "Size": "AS03",
    "ID": "A0631",
    "Brand": "Apple",
    "Model Name": "iPhone 6S Plus",
    "Color": "Gold",
    "Color Code": "AC04",
    "Height": 158.2,
    "Width": 77.9,
    "Depth": 7.3,
    "image": "iPhone6SPlus_Gold.jpg",
    "cal": "",
    "script": ""
  },
  {
    "Size": "AS03",
    "ID": "A0632",
    "Brand": "Apple",
    "Model Name": "iPhone 6S Plus",
    "Color": "Gray",
    "Color Code": "AC05",
    "Height": 158.2,
    "Width": 77.9,
    "Depth": 7.3,
    "image": "iPhone6sPlus_Gray.jpg",
    "cal": "",
    "script": ""
  },
  {
    "Size": "AS03",
    "ID": "A0633",
    "Brand": "Apple",
    "Model Name": "iPhone 6S Plus",
    "Color": "Rose Gold",
    "Color Code": "AC07",
    "Height": 158.2,
    "Width": 77.9,
    "Depth": 7.3,
    "image": "iPhone6SPlus_RoseGold.jpg",
    "cal": "",
    "script": ""
  },
  {
    "Size": "AS03",
    "ID": "A0634",
    "Brand": "Apple",
    "Model Name": "iPhone 6S Plus",
    "Color": "Silver",
    "Color Code": "AC06",
    "Height": 158.2,
    "Width": 77.9,
    "Depth": 7.3,
    "image": "",
    "cal": "",
    "script": ""
  },
  {
    "Size": "AS02",
    "ID": "A0701",
    "Brand": "Apple",
    "Model Name": "iPhone 7",
    "Color": "Gold",
    "Color Code": "AC04",
    "Height": 138.3,
    "Width": 67.1,
    "Depth": 7.1,
    "image": "iPhone7_Gold.jpg",
    "cal": "",
    "script": ""
  },
  {
    "Size": "AS02",
    "ID": "A0702",
    "Brand": "Apple",
    "Model Name": "iPhone 7",
    "Color": "Jet Black",
    "Color Code": "AC08",
    "Height": 138.3,
    "Width": 67.1,
    "Depth": 7.1,
    "image": "iphone7_jetblack.jpg",
    "cal": "",
    "script": ""
  },
  {
    "Size": "AS02",
    "ID": "A0703",
    "Brand": "Apple",
    "Model Name": "iPhone 7",
    "Color": "Matte Black",
    "Color Code": "AC09",
    "Height": 138.3,
    "Width": 67.1,
    "Depth": 7.1,
    "image": "iPhone7_MatteBlack.jpg",
    "cal": "",
    "script": ""
  },
  {
    "Size": "AS02",
    "ID": "A0704",
    "Brand": "Apple",
    "Model Name": "iPhone 7",
    "Color": "Red",
    "Color Code": "AC10",
    "Height": 138.3,
    "Width": 67.1,
    "Depth": 7.1,
    "image": "iPhone7_Red.jpg",
    "cal": "",
    "script": ""
  },
  {
    "Size": "AS02",
    "ID": "A0705",
    "Brand": "Apple",
    "Model Name": "iPhone 7",
    "Color": "Rose Gold",
    "Color Code": "AC07",
    "Height": 138.3,
    "Width": 67.1,
    "Depth": 7.1,
    "image": "iPhone7_RoseGold.jpg",
    "cal": "",
    "script": ""
  },
  {
    "Size": "AS02",
    "ID": "A0706",
    "Brand": "Apple",
    "Model Name": "iPhone 7",
    "Color": "Silver",
    "Color Code": "AC06",
    "Height": 138.3,
    "Width": 67.1,
    "Depth": 7.1,
    "image": "iPhone7_Silver.jpg",
    "cal": "",
    "script": ""
  },
  {
    "Size": "AS03",
    "ID": "A0711",
    "Brand": "Apple",
    "Model Name": "iPhone 7 Plus",
    "Color": "Gold",
    "Color Code": "AC04",
    "Height": 158.2,
    "Width": 77.9,
    "Depth": 7.3,
    "image": "iPhone7Plus_Gold.jpg",
    "cal": "",
    "script": ""
  },
  {
    "Size": "AS03",
    "ID": "A0712",
    "Brand": "Apple",
    "Model Name": "iPhone 7 Plus",
    "Color": "Jet Black",
    "Color Code": "AC08",
    "Height": 158.2,
    "Width": 77.9,
    "Depth": 7.3,
    "image": "iPhone7Plus_JetBlack.jpg",
    "cal": "",
    "script": ""
  },
  {
    "Size": "AS03",
    "ID": "A0713",
    "Brand": "Apple",
    "Model Name": "iPhone 7 Plus",
    "Color": "Matte Black",
    "Color Code": "AC09",
    "Height": 158.2,
    "Width": 77.9,
    "Depth": 7.3,
    "image": "iPhone7Plus_MatteBlack.jpg",
    "cal": "",
    "script": ""
  },
  {
    "Size": "AS03",
    "ID": "A0714",
    "Brand": "Apple",
    "Model Name": "iPhone 7 Plus",
    "Color": "Red",
    "Color Code": "AC10",
    "Height": 158.2,
    "Width": 77.9,
    "Depth": 7.3,
    "image": "iPhone7Plus_Red.jpg",
    "cal": "",
    "script": ""
  },
  {
    "Size": "AS03",
    "ID": "A0715",
    "Brand": "Apple",
    "Model Name": "iPhone 7 Plus",
    "Color": "Rose Gold",
    "Color Code": "AC07",
    "Height": 158.2,
    "Width": 77.9,
    "Depth": 7.3,
    "image": "iphone7plus_RoseGold.jpg",
    "cal": "",
    "script": ""
  },
  {
    "Size": "AS03",
    "ID": "A0716",
    "Brand": "Apple",
    "Model Name": "iPhone 7 Plus",
    "Color": "Silver",
    "Color Code": "AC06",
    "Height": 158.2,
    "Width": 77.9,
    "Depth": 7.3,
    "image": "iPhone7Plus_Silver.jpg",
    "cal": "",
    "script": ""
  },
  {
    "Size": "AS02",
    "ID": "A0801",
    "Brand": "Apple",
    "Model Name": "iPhone 8",
    "Color": "Gold",
    "Color Code": "AC11",
    "Height": 138.4,
    "Width": 67.3,
    "Depth": 7.3,
    "image": "iphone8_gold.png",
    "cal": "",
    "script": ""
  },
  {
    "Size": "AS02",
    "ID": "A0802",
    "Brand": "Apple",
    "Model Name": "iPhone 8",
    "Color": "Red",
    "Color Code": "AC12",
    "Height": 138.4,
    "Width": 67.3,
    "Depth": 7.3,
    "image": "iPhone8_red.jpg",
    "cal": "",
    "script": ""
  },
  {
    "Size": "AS02",
    "ID": "A0803",
    "Brand": "Apple",
    "Model Name": "iPhone 8",
    "Color": "Silver",
    "Color Code": "AC13",
    "Height": 138.4,
    "Width": 67.3,
    "Depth": 7.3,
    "image": "iphone8_silver.png",
    "cal": "",
    "script": ""
  },
  {
    "Size": "AS02",
    "ID": "A0804",
    "Brand": "Apple",
    "Model Name": "iPhone 8",
    "Color": "Space Gray",
    "Color Code": "AC14",
    "Height": 138.4,
    "Width": 67.3,
    "Depth": 7.3,
    "image": "iphone8_gray.png",
    "cal": "",
    "script": ""
  },
  {
    "Size": "AS03",
    "ID": "A0811",
    "Brand": "Apple",
    "Model Name": "iPhone 8 Plus",
    "Color": "Gold",
    "Color Code": "AC11",
    "Height": 158.4,
    "Width": 78.1,
    "Depth": 7.5,
    "image": "iphone8plus_gold.png",
    "cal": "",
    "script": ""
  },
  {
    "Size": "AS03",
    "ID": "A0812",
    "Brand": "Apple",
    "Model Name": "iPhone 8 Plus",
    "Color": "Red",
    "Color Code": "AC12",
    "Height": 158.4,
    "Width": 78.1,
    "Depth": 7.5,
    "image": "iPhone8Plus_red.jpg",
    "cal": "",
    "script": ""
  },
  {
    "Size": "AS03",
    "ID": "A0813",
    "Brand": "Apple",
    "Model Name": "iPhone 8 Plus",
    "Color": "Silver",
    "Color Code": "AC13",
    "Height": 158.4,
    "Width": 78.1,
    "Depth": 7.5,
    "image": "iphone8plus_silver.png",
    "cal": "",
    "script": ""
  },
  {
    "Size": "AS03",
    "ID": "A0814",
    "Brand": "Apple",
    "Model Name": "iPhone 8 Plus",
    "Color": "Space Gray",
    "Color Code": "AC14",
    "Height": 158.4,
    "Width": 78.1,
    "Depth": 7.5,
    "image": "iphone8plus_gray.png",
    "cal": "",
    "script": ""
  },
  {
    "Size": "AS04",
    "ID": "A1001",
    "Brand": "Apple",
    "Model Name": "iPhone X",
    "Color": "Silver",
    "Color Code": "AC13",
    "Height": 143.6,
    "Width": 70.9,
    "Depth": 7.7,
    "image": "iPhoneX_Silver.jpg",
    "cal": "",
    "script": ""
  },
  {
    "Size": "AS04",
    "ID": "A1002",
    "Brand": "Apple",
    "Model Name": "iPhone X",
    "Color": "Space Gray",
    "Color Code": "AC14",
    "Height": 143.6,
    "Width": 70.9,
    "Depth": 7.7,
    "image": "iPhoneX_Gray.jpg",
    "cal": "",
    "script": ""
  },
  {
    "Size": "AS04",
    "ID": "A1011",
    "Brand": "Apple",
    "Model Name": "iPhone Xs",
    "Color": "Gold",
    "Color Code": "AC15",
    "Height": 143.6,
    "Width": 70.9,
    "Depth": 7.7,
    "image": "iPhoneXs_gold.png",
    "cal": "",
    "script": ""
  },
  {
    "Size": "AS04",
    "ID": "A1012",
    "Brand": "Apple",
    "Model Name": "iPhone Xs",
    "Color": "Silver",
    "Color Code": "AC13",
    "Height": 143.6,
    "Width": 70.9,
    "Depth": 7.7,
    "image": "iPhoneXs_silver.png",
    "cal": "",
    "script": ""
  },
  {
    "Size": "AS04",
    "ID": "A1013",
    "Brand": "Apple",
    "Model Name": "iPhone Xs",
    "Color": "Space Gray",
    "Color Code": "AC14",
    "Height": 143.6,
    "Width": 70.9,
    "Depth": 7.7,
    "image": "iPhoneXs_gray.png",
    "cal": "",
    "script": ""
  },
  {
    "Size": "AS05",
    "ID": "A1021",
    "Brand": "Apple",
    "Model Name": "iPhone Xs Max",
    "Color": "Gold",
    "Color Code": "AC15",
    "Height": 157.5,
    "Width": 77.4,
    "Depth": 7.7,
    "image": "iPhoneXsMax_gold.png",
    "cal": "",
    "script": ""
  },
  {
    "Size": "AS05",
    "ID": "A1022",
    "Brand": "Apple",
    "Model Name": "iPhone Xs Max",
    "Color": "Silver",
    "Color Code": "AC13",
    "Height": 157.5,
    "Width": 77.4,
    "Depth": 7.7,
    "image": "iPhoneXsMax_silver.png",
    "cal": "",
    "script": ""
  },
  {
    "Size": "AS05",
    "ID": "A1023",
    "Brand": "Apple",
    "Model Name": "iPhone Xs Max",
    "Color": "Space Gray",
    "Color Code": "AC14",
    "Height": 157.5,
    "Width": 77.4,
    "Depth": 7.7,
    "image": "iPhoneXsMax_gray.png",
    "cal": "",
    "script": ""
  },
  {
    "Size": "AS06",
    "ID": "A1031",
    "Brand": "Apple",
    "Model Name": "iPhone XR",
    "Color": "Black",
    "Color Code": "AC16",
    "Height": 150.9,
    "Width": 75.7,
    "Depth": 8.3,
    "image": "iPhoneXR_black.png",
    "cal": "",
    "script": ""
  },
  {
    "Size": "AS06",
    "ID": "A1032",
    "Brand": "Apple",
    "Model Name": "iPhone XR",
    "Color": "Blue",
    "Color Code": "AC17",
    "Height": 150.9,
    "Width": 75.7,
    "Depth": 8.3,
    "image": "iPhoneXR_blue.png",
    "cal": "",
    "script": ""
  },
  {
    "Size": "AS06",
    "ID": "A1033",
    "Brand": "Apple",
    "Model Name": "iPhone XR",
    "Color": "Coral",
    "Color Code": "AC18",
    "Height": 150.9,
    "Width": 75.7,
    "Depth": 8.3,
    "image": "iPhoneXR_coral.png",
    "cal": "",
    "script": ""
  },
  {
    "Size": "AS06",
    "ID": "A1034",
    "Brand": "Apple",
    "Model Name": "iPhone XR",
    "Color": "White",
    "Color Code": "AC19",
    "Height": 150.9,
    "Width": 75.7,
    "Depth": 8.3,
    "image": "iPhoneXR_white.png",
    "cal": "",
    "script": ""
  },
  {
    "Size": "AS06",
    "ID": "A1035",
    "Brand": "Apple",
    "Model Name": "iPhone XR",
    "Color": "Yellow",
    "Color Code": "AC20",
    "Height": 150.9,
    "Width": 75.7,
    "Depth": 8.3,
    "image": "iPhoneXR_yellow.png",
    "cal": "",
    "script": ""
  },
  {
    "Size": "AS06",
    "ID": "A1036",
    "Brand": "Apple",
    "Model Name": "iPhone XR",
    "Color": "Red",
    "Color Code": "AC21 (AC12)",
    "Height": 150.9,
    "Width": 75.7,
    "Depth": 8.3,
    "image": "iPhoneXR_red.png",
    "cal": "",
    "script": ""
  }
]